meshai/__init__.py
meshai/data_handler.py
meshai/domain_manager.py
meshai/logger.py
meshai/model_handler.py
meshai/security.py
meshai/utils.py
meshai-0.1.4.dist-info/LICENSE
meshai-0.1.4.dist-info/METADATA
meshai-0.1.4.dist-info/WHEEL
meshai-0.1.4.dist-info/top_level.txt
meshai-0.1.4.dist-info/RECORD
