Metadata-Version: 2.1
Name: meshai
Version: 0.1.4
Summary: MeshAI SDK for decentralized AI model development
Home-page: https://github.com/robbie/meshai-sdk
Author: Robbie (Ravi Tiwari)
Author-email: your.email@example.com
License: MIT
Classifier: Programming Language :: Python :: 3
Classifier: License :: OSI Approved :: MIT License
Classifier: Operating System :: OS Independent
Requires-Python: >=3.7
License-File: LICENSE
Requires-Dist: torch
Requires-Dist: torchvision
Requires-Dist: transformers
Requires-Dist: pandas
Requires-Dist: scikit-learn
Requires-Dist: numpy
Requires-Dist: joblib
Requires-Dist: Pillow
Requires-Dist: PyPDF2
Requires-Dist: cryptography
